test_hugo/__init__.py
test_hugo/core/__init__.py
test_hugo/core/cli.py
test_hugo/core/connection.py
test_hugo/core/core.py
test_hugo/core/provider.py
test_hugo/core/workflow.py
test_hugo/utils/__init__.py
test_hugo/utils/definitions.py
test_hugo/utils/exceptions.py
test_hugo-0.8.0.dist-info/LICENCE
test_hugo-0.8.0.dist-info/METADATA
test_hugo-0.8.0.dist-info/WHEEL
test_hugo-0.8.0.dist-info/RECORD
