Metadata-Version: 2.3
Name: test-hugo
Version: 0.8.0
Summary: An MLflow plugin that enables natural language conversations with your MLflow server using LLM providers like OpenAI and Ollama.
License: Apache-2.0
Author: Hugo Carvalho
Author-email: hugodanielsilvacarvalho.hc@gmail.com
Requires-Python: >=3.9
Classifier: License :: OSI Approved :: Apache Software License
Classifier: Programming Language :: Python :: 3
Classifier: Programming Language :: Python :: 3.9
Classifier: Programming Language :: Python :: 3.10
Classifier: Programming Language :: Python :: 3.11
Classifier: Programming Language :: Python :: 3.12
Classifier: Programming Language :: Python :: 3.13
